{"initDir":"/home/runner/work/nova/nova/docs","cfgDir":"/home/runner/work/nova/nova/docs","rawCfg":"[nimib]\nsrcDir = \"book\"\nhomeDir = \"../out\"\n\n[nimibook]\nlanguage = \"en-us\"\ntitle = \"Nova\"\ndescription = \"Nova CLI Documentation\"\n","nbCfg":{"srcDir":"book","homeDir":"../out"},"cfg":{"title":"Nova","language":"en-us","description":"Nova CLI Documentation","default_theme":"light","preferred_dark_theme":"navy","git_repository_url":"","git_repository_icon":"fa-github","plausible_analytics_url":"","favicon_escaped":"<link rel=\"icon\" href=\"data:image/svg+xml,<svg xmlns=%22http://www.w3.org/2000/svg%22 viewBox=%220 0 100 100%22><text y=%22.9em%22 font-size=%2280%22>🐳</text></svg>\">"},"theme_option":{"navy":"Navy","coal":"Coal","rust":"Rust","ayu":"Ayu","light":"Light (default)"},"toc":{"entries":[{"title":"Introduction","path":"index.md","levels":[1],"isNumbered":true,"isDraft":false,"isActive":false},{"title":"How to Get Govee API Key","path":"api-key.md","levels":[2],"isNumbered":true,"isDraft":false,"isActive":false},{"title":"Commands","path":"commands.md","levels":[3],"isNumbered":true,"isDraft":false,"isActive":false},{"title":"Setup","path":"commands/setup.md","levels":[3,1],"isNumbered":true,"isDraft":false,"isActive":false},{"title":"Turn","path":"commands/turn.md","levels":[3,2],"isNumbered":true,"isDraft":false,"isActive":false},{"title":"Brightness","path":"commands/brightness.md","levels":[3,3],"isNumbered":true,"isDraft":false,"isActive":false},{"title":"Color","path":"commands/color.md","levels":[3,4],"isNumbered":true,"isDraft":false,"isActive":false},{"title":"Color Temp","path":"commands/color-temp.md","levels":[3,5],"isNumbered":true,"isDraft":false,"isActive":false},{"title":"State","path":"commands/state.md","levels":[3,6],"isNumbered":true,"isDraft":false,"isActive":false},{"title":"RGB","path":"commands/rgb.md","levels":[3,7],"isNumbered":true,"isDraft":false,"isActive":false},{"title":"Picker","path":"commands/picker.md","levels":[3,8],"isNumbered":true,"isDraft":false,"isActive":false},{"title":"Devices","path":"commands/devices.md","levels":[3,9],"isNumbered":true,"isDraft":false,"isActive":false},{"title":"Version","path":"commands/version.md","levels":[3,10],"isNumbered":true,"isDraft":false,"isActive":false},{"title":"About","path":"commands/about.md","levels":[3,11],"isNumbered":true,"isDraft":false,"isActive":false},{"title":"Description","path":"commands/description.md","levels":[3,12],"isNumbered":true,"isDraft":false,"isActive":false},{"title":"Source","path":"commands/source.md","levels":[3,13],"isNumbered":true,"isDraft":false,"isActive":false},{"title":"Repo","path":"commands/repo.md","levels":[3,14],"isNumbered":true,"isDraft":false,"isActive":false},{"title":"License","path":"commands/license.md","levels":[3,15],"isNumbered":true,"isDraft":false,"isActive":false},{"title":"Docs","path":"commands/docs.md","levels":[3,16],"isNumbered":true,"isDraft":false,"isActive":false}]},"keep":[]}